{"nodes": [{"id": "tools_latentsync_eval_detectors_readme", "label": "Face detector README (adapted from cs-giung/face-detection-pytorch)", "file_type": "document", "source_file": "tools/LatentSync/eval/detectors/README.md", "source_location": null, "source_url": null, "captured_at": null, "author": null, "contributor": null}], "edges": [{"source": "tools_latentsync_eval_detectors_readme", "target": "tools_latentsync_tool", "relation": "evaluation_component_of", "confidence": "EXTRACTED", "confidence_score": 1.0, "source_file": "tools/LatentSync/eval/detectors/README.md", "source_location": null, "weight": 1.0}], "hyperedges": []}